ldtc/__init__.py
ldtc/arbiter/policy.py
ldtc/arbiter/refusal.py
ldtc/attest/exporter.py
ldtc/attest/indicators.py
ldtc/attest/keys.py
ldtc/cli/main.py
ldtc/guardrails/audit.py
ldtc/guardrails/dt_guard.py
ldtc/guardrails/lreg.py
ldtc/guardrails/smelltests.py
ldtc/lmeas/diagnostics.py
ldtc/lmeas/estimators.py
ldtc/lmeas/metrics.py
ldtc/lmeas/partition.py
ldtc/omega/command_conflict.py
ldtc/omega/ingress_flood.py
ldtc/omega/power_sag.py
ldtc/plant/adapter.py
ldtc/plant/hw_adapter.py
ldtc/plant/models.py
ldtc/plant/scenarios.py
ldtc/reporting/artifacts.py
ldtc/reporting/style.py
ldtc/reporting/tables.py
ldtc/reporting/timeline.py
ldtc/runtime/scheduler.py
ldtc/runtime/windows.py
ldtc-1.0.0.dist-info/licenses/LICENSE
ldtc-1.0.0.dist-info/METADATA
ldtc-1.0.0.dist-info/WHEEL
ldtc-1.0.0.dist-info/entry_points.txt
ldtc-1.0.0.dist-info/top_level.txt
ldtc-1.0.0.dist-info/RECORD
