Metadata-Version: 2.4
Name: ldtc
Version: 1.0.0
Summary: Single-machine, real-time digital boundary organism: NC1/SC1 verification harness.
Author: Owen Carey
License: MIT
Requires-Python: >=3.9
License-File: LICENSE
Requires-Dist: numpy>=1.26
Requires-Dist: scikit-learn>=1.3
Requires-Dist: PyYAML>=6.0
Requires-Dist: cryptography>=42.0
Requires-Dist: cbor2>=5.6
Requires-Dist: matplotlib>=3.8
Requires-Dist: statsmodels>=0.14
Requires-Dist: graphviz>=0.20.3
Provides-Extra: dev
Requires-Dist: pytest>=8.0; extra == "dev"
Requires-Dist: black>=24.0; extra == "dev"
Requires-Dist: ruff>=0.4; extra == "dev"
Requires-Dist: mypy>=1.10; extra == "dev"
Requires-Dist: types-PyYAML>=6.0.12.20240311; extra == "dev"
Requires-Dist: ipykernel>=6.29; extra == "dev"
Dynamic: license-file
